{
  "id": "1",
  "title": "Nagłówek drzewa",
  "subtitle": "wielowierszowy",
  "type": "checkbox",
  "content": [
    {
      "id": "2",
      "title": "Pododdział 1",
      "type": "radio",
      "content": [
        {
          "title": "Zespół 1",
          "subtitle": "HR"
        },
        {
          "title": "Zespół 2",
          "subtitle": "Marketing"
        },
        {
          "id": "3",
          "title": "Zespół 3",
          "subtitle": "Analitycy",
          "type": "checkbox",
          "content": [
            {
              "title": "Podzespół 3.1",
              "subtitle": "Kalendarz"
            },
            {
              "title": "Podzespół 3.2",
              "subtitle": "Kokpit"
            },
            {
              "title": "Podzespół 3.3",
              "subtitle": "Widok"
            },
            {
              "title": "Podzespół 3.4",
              "subtitle": "Różności"
            },
            {
              "title": "Podzespół 3.5",
              "subtitle": "Szukaj"
            }
          ]
        },
        {
          "id": "4",
          "title": "Zespół 4",
          "subtitle": "Programiści",
          "type": "checkbox",
          "content": [
            {
              "title": "Podzespół 4.1",
              "subtitle": "Front-end"
            },
            {
              "title": "Podzespół 4.2",
              "subtitle": "Middle-front-end"
            },
            {
              "title": "Podzespół 4.3",
              "subtitle": "Middle-end"
            },
            {
              "title": "Podzespół 4.4",
              "subtitle": "Middle-back-end"
            },
            {
              "title": "Podzespół 4.5",
              "subtitle": "Back-end"
            }
          ]
        }
      ]
    },
    {
      "id": "5",
      "title": "Pododdział 2",
      "type": "radio",
      "content": [
        {
          "title": "Zespół 1",
          "subtitle": "HR"
        },
        {
          "title": "Zespół 2",
          "subtitle": "Marketing"
        },
        {
          "id": "6",
          "title": "Zespół 3",
          "subtitle": "Analitycy",
          "type": "checkbox",
          "content": [
            {
              "title": "Podzespół 3.1",
              "subtitle": "Kalendarz"
            },
            {
              "title": "Podzespół 3.2",
              "subtitle": "Kokpit"
            },
            {
              "title": "Podzespół 3.3",
              "subtitle": "Widok"
            },
            {
              "title": "Podzespół 3.4",
              "subtitle": "Różności"
            },
            {
              "title": "Podzespół 3.5",
              "subtitle": "Szukaj"
            }
          ]
        },
        {
          "id": "7",
          "title": "Zespół 4",
          "subtitle": "Programiści",
          "type": "checkbox",
          "content": [
            {
              "title": "Podzespół 4.1",
              "subtitle": "Front-end"
            },
            {
              "title": "Podzespół 4.2",
              "subtitle": "Middle-front-end"
            },
            {
              "title": "Podzespół 4.3",
              "subtitle": "Middle-end"
            },
            {
              "title": "Podzespół 4.4",
              "subtitle": "Middle-back-end"
            },
            {
              "title": "Podzespół 4.5",
              "subtitle": "Back-end"
            }
          ]
        }
      ]

    },
    {
      "id": "8",
      "title": "Pododdział 3",
      "type": "radio",
      "content": [
        {
          "title": "Zespół 1",
          "subtitle": "HR"
        },
        {
          "title": "Zespół 2",
          "subtitle": "Marketing"
        },
        {
          "id": "9",
          "title": "Zespół 3",
          "subtitle": "Analitycy",
          "type": "checkbox",
          "content": [
            {
              "title": "Podzespół 3.1",
              "subtitle": "Kalendarz"
            },
            {
              "title": "Podzespół 3.2",
              "subtitle": "Kokpit"
            },
            {
              "title": "Podzespół 3.3",
              "subtitle": "Widok"
            },
            {
              "title": "Podzespół 3.4",
              "subtitle": "Różności"
            },
            {
              "title": "Podzespół 3.5",
              "subtitle": "Szukaj"
            }
          ]
        },
        {
          "id": "10",
          "title": "Zespół 4",
          "subtitle": "Programiści",
          "type": "checkbox",
          "content": [
            {
              "title": "Podzespół 4.1",
              "subtitle": "Front-end"
            },
            {
              "title": "Podzespół 4.2",
              "subtitle": "Middle-front-end"
            },
            {
              "title": "Podzespół 4.3",
              "subtitle": "Middle-end"
            },
            {
              "title": "Podzespół 4.4",
              "subtitle": "Middle-back-end"
            },
            {
              "title": "Podzespół 4.5",
              "subtitle": "Back-end"
            }
          ]
        }
      ]
    },
    {
      "title": "Niezrzeszeni"
    }
  ]
}
